past_mtl_monitors/__init__.py
past_mtl_monitors/monitors.py
past_mtl_monitors-0.1.0.dist-info/LICENSE
past_mtl_monitors-0.1.0.dist-info/WHEEL
past_mtl_monitors-0.1.0.dist-info/METADATA
past_mtl_monitors-0.1.0.dist-info/RECORD
