Metadata-Version: 2.1
Name: past-mtl-monitors
Version: 0.1.0
Summary: A library for creating past metric temporal logic monitors.
Home-page: https://github.com/mvcisback/past-mtl-monitors
Author: Marcell Vazquez-Chanlatte
Author-email: mvc@linux.com
Requires-Python: >=3.8,<4.0
Classifier: Programming Language :: Python :: 3
Classifier: Programming Language :: Python :: 3.8
Requires-Dist: attrs (>=19.3.0,<20.0.0)
Requires-Dist: intervaltree (>=3.0.2,<4.0.0)
Project-URL: Repository, https://github.com/mvcisback/past-mtl-monitors
